main.py
utils.py
pytype_b1-0.1.0.dist-info/METADATA
pytype_b1-0.1.0.dist-info/WHEEL
pytype_b1-0.1.0.dist-info/entry_points.txt
pytype_b1-0.1.0.dist-info/top_level.txt
pytype_b1-0.1.0.dist-info/RECORD
