Metadata-Version: 2.4
Name: Pytype-B1
Version: 0.1.0
Summary: A terminal-based typing speed test using python.
Home-page: https://github.com/basanta-bhandari/Pytype
Author: Basanta Bhandari
Author-email: bhandari.basanta.47@gmail.com
Classifier: Programming Language :: Python :: 3
Classifier: Programming Language :: Python :: 3.7
Classifier: Programming Language :: Python :: 3.8
Classifier: Programming Language :: Python :: 3.9
Classifier: Programming Language :: Python :: 3.10
Classifier: Programming Language :: Python :: 3.11
Classifier: License :: OSI Approved :: MIT License
Classifier: Operating System :: OS Independent
Classifier: Environment :: Console :: Curses
Classifier: Topic :: Games/Entertainment
Requires-Python: >=3.7
Requires-Dist: windows-curses>=2.3.0; sys_platform == "win32"
Dynamic: author
Dynamic: author-email
Dynamic: classifier
Dynamic: description
Dynamic: description-content-type
Dynamic: home-page
Dynamic: requires-dist
Dynamic: requires-python
Dynamic: summary
